ravdec/__init__.py
ravdec-3.4.dist-info/METADATA
ravdec-3.4.dist-info/WHEEL
ravdec-3.4.dist-info/top_level.txt
ravdec-3.4.dist-info/RECORD
