Metadata-Version: 2.1
Name: ravdec
Version: 3.4
Summary: Ravdec - Lossless Data Compression
Home-page: https://github.com/mr-ravin/ravdec
Author: Ravin Kumar
Author-email: mr.ravin_kumar@hotmail.com
License: MIT
Keywords: data compression,lossless compression,file compression,text compression,efficient compression
Classifier: Programming Language :: Python :: 3
Classifier: License :: OSI Approved :: MIT License
Classifier: Operating System :: OS Independent
Requires-Python: >=3.7
